{
  "persons": [
    {
      "name": "Arto Hellas",
      "number": "0124",
      "id": "1"
    },
    {
      "name": "Ada Lovelace",
      "number": "39-44-5323523",
      "id": "2"
    },
    {
      "name": "Dan Abramov",
      "number": "12-43-234345",
      "id": "3"
    },
    {
      "name": "Mary Poppendieck",
      "number": "39-23-6423122",
      "id": "4"
    },
    {
      "id": "5547",
      "name": "ewfew",
      "number": "23"
    },
    {
      "id": "afda",
      "name": "ewf1",
      "number": "244"
    },
    {
      "id": "78e2",
      "name": "wfewef",
      "number": "22222"
    },
    {
      "id": "631a",
      "name": "",
      "number": ""
    },
    {
      "id": "df50",
      "name": "efwwef",
      "number": "123"
    },
    {
      "id": "761b",
      "name": "sdf",
      "number": "1245"
    },
    {
      "id": "624d",
      "name": "fegerger",
      "number": "1111345"
    },
    {
      "id": "a323",
      "name": "dsafsdf",
      "number": "11"
    },
    {
      "id": "a3cf",
      "name": "werewr",
      "number": "124"
    }
  ]
}